{
	"AE": {
		"title_id": "00040000000DF000"
	},
	"AI": {
		"title_id": "00040000000DF000"
	},
	"BR": {
		"title_id": "00040000000DF000"
	},
	"AU": {
		"title_id": "00040000000DF000"
	},
	"BO": {
		"title_id": "00040000000DF000"
	},
	"AR": {
		"title_id": "00040000000DF000"
	},
	"AT": {
		"title_id": "00040000000DF000"
	},
	"BG": {
		"title_id": "00040000000DF000"
	},
	"AW": {
		"title_id": "00040000000DF000"
	},
	"BS": {
		"title_id": "00040000000DF000"
	},
	"BM": {
		"title_id": "00040000000DF000"
	},
	"BZ": {
		"title_id": "00040000000DF000"
	},
	"CA": {
		"title_id": "00040000000DF000"
	},
	"BE": {
		"title_id": "00040000000DF000"
	},
	"CZ": {
		"title_id": "00040000000DF000"
	},
	"CO": {
		"title_id": "00040000000DF000"
	},
	"CL": {
		"title_id": "00040000000DF000"
	},
	"BB": {
		"title_id": "00040000000DF000"
	},
	"HN": {
		"title_id": "00040000000DF000"
	},
	"ES": {
		"title_id": "00040000000DF000"
	},
	"FR": {
		"title_id": "00040000000DF000"
	},
	"GP": {
		"title_id": "00040000000DF000"
	},
	"CR": {
		"title_id": "00040000000DF000"
	},
	"DM": {
		"title_id": "00040000000DF000"
	},
	"AG": {
		"title_id": "00040000000DF000"
	},
	"KR": {
		"title_id": "00040000000DF000"
	},
	"CY": {
		"title_id": "00040000000DF000"
	},
	"GD": {
		"title_id": "00040000000DF000"
	},
	"CH": {
		"title_id": "00040000000DF000"
	},
	"DK": {
		"title_id": "00040000000DF000"
	},
	"EE": {
		"title_id": "00040000000DF000"
	},
	"GT": {
		"title_id": "00040000000DF000"
	},
	"EC": {
		"title_id": "00040000000DF000"
	},
	"FI": {
		"title_id": "00040000000DF000"
	},
	"GF": {
		"title_id": "00040000000DF000"
	},
	"AN": {
		"title_id": "00040000000DF000"
	},
	"MY": {
		"title_id": "00040000000DF000"
	},
	"PE": {
		"title_id": "00040000000DF000"
	},
	"JM": {
		"title_id": "00040000000DF000"
	},
	"IT": {
		"title_id": "00040000000DF000"
	},
	"KY": {
		"title_id": "00040000000DF000"
	},
	"MQ": {
		"title_id": "00040000000DF000"
	},
	"IE": {
		"title_id": "00040000000DF000"
	},
	"HU": {
		"title_id": "00040000000DF000"
	},
	"KN": {
		"title_id": "00040000000DF000"
	},
	"HT": {
		"title_id": "00040000000DF000"
	},
	"LC": {
		"title_id": "00040000000DF000"
	},
	"HR": {
		"title_id": "00040000000DF000"
	},
	"JP": {
		"title_id": "00040000000DF000",
		"eshop_id": "50010000015060",
		"product_code": "CTR-N-TDAJ",
		"name": "バイナリィランド",
		"platform": 24,
		"platform_device": "CTR",
		"publisher": 149,
		"banner_url": null,
		"icon_url": "https://kanzashi-wup.cdn.nintendo.net/i/f8135392b54b6dc086660cd28d936bad14712882ab0b50555d009e6af03b0d8d.jpg",
		"data_size": "6179684",
		"description": "このソフトは、1985年に発売されたファミリーコンピュータ用のアクションパズルゲームです。 鏡の迷路に閉じ込められたペンギンのグリンとマロン。グリンが左に動くとマロンは右に動く、といったように、2人は左右逆の動きをします。残り時間が０になるまでに、2人同時に出口にたどり着くとクリアとなり、次のラウンドに進みます。迷路に出現する敵を倒したり利用したりしながら、2人同時に出口にたどり着くよう導きます。",
		"availability": {
			"eshop": true,
			"retail": false,
			"dates": {
				"eshop": "2013-08-07",
				"retail": null
			}
		},
		"screenshots": [
			{
				"upper": "https://kanzashi-wup.cdn.nintendo.net/i/5fdc7ee60721716a82a8d276d500148e3a9b32809b286230b0a739e6ccc54000.jpg",
				"lower": "https://kanzashi-wup.cdn.nintendo.net/i/698a1212e4d509882d82c79744f902b7489b1a66116047b5be9db82a15f51b11.jpg"
			},
			{
				"upper": "https://kanzashi-wup.cdn.nintendo.net/i/0d29b93f83e9a57c4073e68b2d4211fd5439545830042fecabf002cd8cb36b1c.jpg",
				"lower": "https://kanzashi-wup.cdn.nintendo.net/i/698a1212e4d509882d82c79744f902b7489b1a66116047b5be9db82a15f51b11.jpg"
			},
			{
				"upper": "https://kanzashi-wup.cdn.nintendo.net/i/150b9d97f183e5b9744e9cdecc1fedf540071ec0dba62f7bb37f68cf8dfef045.jpg",
				"lower": "https://kanzashi-wup.cdn.nintendo.net/i/698a1212e4d509882d82c79744f902b7489b1a66116047b5be9db82a15f51b11.jpg"
			}
		],
		"movies": []
	},
	"MS": {
		"title_id": "00040000000DF000"
	},
	"LT": {
		"title_id": "00040000000DF000"
	},
	"SK": {
		"title_id": "00040000000DF000"
	},
	"NZ": {
		"title_id": "00040000000DF000"
	},
	"MT": {
		"title_id": "00040000000DF000"
	},
	"LV": {
		"title_id": "00040000000DF000"
	},
	"NO": {
		"title_id": "00040000000DF000"
	},
	"MX": {
		"title_id": "00040000000DF000"
	},
	"LU": {
		"title_id": "00040000000DF000"
	},
	"NL": {
		"title_id": "00040000000DF000"
	},
	"NI": {
		"title_id": "00040000000DF000"
	},
	"PA": {
		"title_id": "00040000000DF000"
	},
	"GB": {
		"title_id": "00040000000DF000"
	},
	"GY": {
		"title_id": "00040000000DF000"
	},
	"DO": {
		"title_id": "00040000000DF000"
	},
	"DE": {
		"title_id": "00040000000DF000"
	},
	"GR": {
		"title_id": "00040000000DF000"
	},
	"HK": {
		"title_id": "00040000000DF000"
	},
	"TC": {
		"title_id": "00040000000DF000"
	},
	"SI": {
		"title_id": "00040000000DF000"
	},
	"TR": {
		"title_id": "00040000000DF000"
	},
	"PL": {
		"title_id": "00040000000DF000"
	},
	"PT": {
		"title_id": "00040000000DF000"
	},
	"SE": {
		"title_id": "00040000000DF000"
	},
	"PY": {
		"title_id": "00040000000DF000"
	},
	"SR": {
		"title_id": "00040000000DF000"
	},
	"SG": {
		"title_id": "00040000000DF000"
	},
	"RO": {
		"title_id": "00040000000DF000"
	},
	"ZA": {
		"title_id": "00040000000DF000"
	},
	"UY": {
		"title_id": "00040000000DF000"
	},
	"VC": {
		"title_id": "00040000000DF000"
	},
	"VI": {
		"title_id": "00040000000DF000"
	},
	"VG": {
		"title_id": "00040000000DF000"
	},
	"VE": {
		"title_id": "00040000000DF000"
	},
	"US": {
		"title_id": "00040000000DF000"
	},
	"TT": {
		"title_id": "00040000000DF000"
	},
	"SA": {
		"title_id": "00040000000DF000"
	},
	"RU": {
		"title_id": "00040000000DF000"
	},
	"SV": {
		"title_id": "00040000000DF000"
	},
	"TW": {
		"title_id": "00040000000DF000"
	}
}