{
	"title_id": "000400000F701900",
	"eshop_id": "50010000039742",
	"product_code": "KTR-N-UAFE",
	"name": "F-ZERO™",
	"platform": 1004,
	"platform_device": "CTR",
	"publisher": 190,
	"banner_url": null,
	"icon_url": "https://kanzashi-wup.cdn.nintendo.net/i/de11d29cce7c0d775323501ad59b5893e561207c5a83b22d726fa939f5eefc1f.jpg",
	"data_size": "5106532",
	"description": "In het jaar 2560 is de grootste racecompetitie het F-ZERO-kampioenschap. Piloten uit de hele melkweg wagen hun leven in een supersnelle strijd tussen turbo-hovercrafts. Door sterk gebruik van het \"Mode 7™\"-effect van de Super Nintendo Entertainment System, legde F-ZERO de lat voor racespellen een stuk hoger met soepele, snelle graphics en een spannende gameplay. F-ZERO pronkte ook met ook een van de beroemdste videogamesoundtracks en liet de spelers kennismaken met onder andere Captain Falcon en Samurai Goroh. Dit is de Amerikaanse versie van het spel.",
	"availability": {
		"eshop": true,
		"retail": false,
		"dates": {
			"eshop": "2016-03-17",
			"retail": null
		}
	},
	"screenshots": [
		{
			"upper": "https://kanzashi-wup.cdn.nintendo.net/i/1c211d438df861f693ee1d06eb0d56b6b719652aa6497e10179ec7f9f998c074.jpg",
			"lower": "https://kanzashi-wup.cdn.nintendo.net/i/349371c69f87817252834b06475e5b7efa51ff330456f24cc0d2aafea3308576.jpg"
		},
		{
			"upper": "https://kanzashi-wup.cdn.nintendo.net/i/81630e9a7bd9cca65fde8500f902099fa48db226f49978b307b7c8a5f2897c09.jpg",
			"lower": "https://kanzashi-wup.cdn.nintendo.net/i/349371c69f87817252834b06475e5b7efa51ff330456f24cc0d2aafea3308576.jpg"
		},
		{
			"upper": "https://kanzashi-wup.cdn.nintendo.net/i/aa8a981dbb6635e3c3dc7fc8e8975eee1620847c2067334df32f5fb351168679.jpg",
			"lower": "https://kanzashi-wup.cdn.nintendo.net/i/349371c69f87817252834b06475e5b7efa51ff330456f24cc0d2aafea3308576.jpg"
		}
	],
	"movies": []
}