{
	"title_id": "000400000013BE00",
	"eshop_id": "50010000025195",
	"product_code": "CTR-P-BS9P",
	"name": "Skylanders Trap Team™",
	"platform": 18,
	"platform_device": "CTR",
	"publisher": 7,
	"banner_url": null,
	"icon_url": "https://kanzashi-wup.cdn.nintendo.net/i/32485b95e85dbd32e4c279c84f617a6e57ab9d90c25eeeb65fe2799d36e60ddf.jpg",
	"data_size": null,
	"description": "Villainous nightmare creatures have escaped from the Realm of Dreams and placed all of Skylands under a terrible sleep spell. You and the Skylanders now have the amazing ability to capture the villains and return them to Skylands to fight for you! Begin the ultimate 3D adventure as you explore Skylands in search of the escaped villains!",
	"availability": {
		"eshop": false,
		"retail": true,
		"dates": {
			"eshop": null,
			"retail": "2014-10-05"
		}
	},
	"screenshots": [
		{
			"upper": "https://kanzashi-wup.cdn.nintendo.net/i/4fff858ef61660d9bab5466562a56359ad32f51eeebc9217375644ca6a06b410.jpg",
			"lower": "https://kanzashi-wup.cdn.nintendo.net/i/0e512c927a6d636b381ac7cdae1bee152f0035f932c6fe825118b716d2e7096c.jpg"
		},
		{
			"upper": "https://kanzashi-wup.cdn.nintendo.net/i/bb9b507383bad9522d15ce972b16faaa534144ec1efd276f658f43ec525a69a3.jpg",
			"lower": "https://kanzashi-wup.cdn.nintendo.net/i/c43a5e6a79d0eeeecb97f8057c97454261447e58d71cdf6e539772c49cfb3ec0.jpg"
		},
		{
			"upper": "https://kanzashi-wup.cdn.nintendo.net/i/f08781330adb5df2196980619793e49b810bf9f6474f421d7f8a03686aeb447f.jpg",
			"lower": "https://kanzashi-wup.cdn.nintendo.net/i/b4094e70251fd1fc999944119a3d3bd8f0e2d9a2afc45443fa4542058604a2d0.jpg"
		}
	],
	"movies": []
}