{
	"title_id": "0004000000076500",
	"eshop_id": "50010000013419",
	"product_code": "CTR-P-AGGP",
	"name": "Luigi’s Mansion™ 2",
	"platform": 103,
	"platform_device": "CTR",
	"publisher": 190,
	"banner_url": null,
	"icon_url": "https://kanzashi-wup.cdn.nintendo.net/i/15f085c0b26b30269e3f794d63220c3ccff83a5605da8093835cf6cd3c2ce5f3.jpg",
	"data_size": "884845460",
	"description": "In Luigi's Mansion 2 per Nintendo 3DS la tua missione sarà quella di eliminare i fantasmi che infestano alcune spaventosissime dimore. Armato del suo fido Poltergust, una specie di aspirapolvere risucchia-fantasmi, il fratellino di Mario è protagonista di questa divertente caccia al fantasma. Non essendo certo un tipo coraggioso, Luigi affronta la sua missione con molta riluttanza, ma a volte anche un eroe fifone può raggiungere il successo! Questo divertente gioco, il primo sequel del titolo Luigi's Mansion uscito nel 2002 per il lancio di Nintendo GameCube, aggiunge ai brividi dell'originale un sacco di nuove e divertenti funzioni. Grazie alla stupefacente grafica in 3D stereoscopico, le tenebrose dimore, i pallidi fantasmi e i lugubri ambienti prendono vita come mai prima d'ora, in un gioco che ti regalerà emozioni spettrali e un divertimento soprannaturale.",
	"availability": {
		"eshop": true,
		"retail": true,
		"dates": {
			"eshop": "2013-03-28",
			"retail": "2013-03-28"
		}
	},
	"screenshots": [
		{
			"upper": "https://kanzashi-wup.cdn.nintendo.net/i/1b0105ca39c27137ed0bdab2fc212a2324b623c3dfe346a566d387671816e530.jpg",
			"lower": "https://kanzashi-wup.cdn.nintendo.net/i/f7a1b0df2ad5706ba8a9b4872d3c2678a6f7fb9b90d60f6b76bd15a677b27ae8.jpg"
		},
		{
			"upper": "https://kanzashi-wup.cdn.nintendo.net/i/78a9c0fcd5e67e151bc9ab31968cede15893c4aae50ec68a74d143d31118d1b1.jpg",
			"lower": "https://kanzashi-wup.cdn.nintendo.net/i/3ab3d360f442a19a730ff132073ed85d8baa6f5485dfe58249871476b7c298bd.jpg"
		},
		{
			"upper": "https://kanzashi-wup.cdn.nintendo.net/i/576ce7a6906ad55995c88d850e890c4fdf2709e365fd713e3d2e36c33f89043e.jpg",
			"lower": "https://kanzashi-wup.cdn.nintendo.net/i/2fc0180738d508da57fe3bedd9221b4df24102c0f1ab99ca4ccb5b41526a5c6d.jpg"
		}
	],
	"movies": [
		{
			"banner_url": "https://kanzashi-wup.cdn.nintendo.net/i/097933234d87953194e72902d661380b13e5209377ad3fca308891d9c3701f02.jpg",
			"name": "Luigi’s Mansion™ 2: teaser trailer",
			"files": [
				{
					"quality": "HQ",
					"format": "mp4",
					"movie_url": "https://kanzashi-movie-wup.cdn.nintendo.net/m/391ee6064096c221841c43b5ba25c8ac01e9874bf8a4be34af7d193bc14c704b.mp4",
					"width": "1280",
					"height": "720",
					"dimension": "2d",
					"play_time_sec": "75"
				},
				{
					"quality": "LQ",
					"format": "mp4",
					"movie_url": "https://kanzashi-movie-wup.cdn.nintendo.net/m/19c04a3444ae7a57aee014019c5bfa657330ee21aebdf54a8ca86eb6c7c9cfca.mp4",
					"width": "853",
					"height": "480",
					"dimension": "2d",
					"play_time_sec": "75"
				}
			]
		},
		{
			"banner_url": "https://kanzashi-wup.cdn.nintendo.net/i/2868d60e372a65af7a11f442d2202591ce012d6cdfba6263b253054c18311061.jpg",
			"name": "Luigi's Mansion™ 2: Video con Shigeru Miyamoto",
			"files": [
				{
					"quality": "HQ",
					"format": "mp4",
					"movie_url": "https://kanzashi-movie-wup.cdn.nintendo.net/m/56c7bf641ef530a5d62783329cf204d79442f74ccc888e7858580530e4969ca6.mp4",
					"width": "1280",
					"height": "720",
					"dimension": "2d",
					"play_time_sec": "307"
				},
				{
					"quality": "LQ",
					"format": "mp4",
					"movie_url": "https://kanzashi-movie-wup.cdn.nintendo.net/m/b8bc7cf76f36b5c2b7c3e37f2b2ac975f0bf815c24ed825393243ccbb7f04302.mp4",
					"width": "853",
					"height": "480",
					"dimension": "2d",
					"play_time_sec": "307"
				}
			]
		},
		{
			"banner_url": "https://kanzashi-wup.cdn.nintendo.net/i/097933234d87953194e72902d661380b13e5209377ad3fca308891d9c3701f02.jpg",
			"name": "Luigi’s Mansion™ 2: trailer",
			"files": [
				{
					"quality": "HQ",
					"format": "mp4",
					"movie_url": "https://kanzashi-movie-wup.cdn.nintendo.net/m/61bce6fedddeb762260c7a03ea07d0dfedc90a6927c5de23930a04c7eb613073.mp4",
					"width": "1280",
					"height": "720",
					"dimension": "2d",
					"play_time_sec": "131"
				},
				{
					"quality": "LQ",
					"format": "mp4",
					"movie_url": "https://kanzashi-movie-wup.cdn.nintendo.net/m/2b9b240e5220fd58d59a2c21fa85f0f057d5c1e001918b692884ab93a7db89b3.mp4",
					"width": "854",
					"height": "480",
					"dimension": "2d",
					"play_time_sec": "131"
				}
			]
		}
	]
}