{
	"title_id": "00040000001C7800",
	"eshop_id": "50010000043275",
	"product_code": "CTR-P-A9CK",
	"name": "Cube Creator DX",
	"platform": 18,
	"platform_device": "CTR",
	"publisher": 19,
	"banner_url": null,
	"icon_url": null,
	"data_size": null,
	"description": "『Cube Creator DX』제품판은 패키지를 구입하여 즐겨 주십시오. 큐브 세계를 다양하게 즐겨보자! 다양한 큐브로 이뤄진 세계를 모험할 수 있는 서바이벌부터, 여러가지 큐브를 가지고 그림을 그리거나 건물, 세계, 스테이지 등 상상하는 모든 것을 자유롭게 만들 수 있는 크리에이티브까지! 가까이 있는 친구부터 멀리 있는 유저까지 최대 4명까지 다함께 놀 수 있는 멀티플레이 대응!",
	"availability": {
		"eshop": false,
		"retail": true,
		"dates": {
			"eshop": null,
			"retail": "2017-09-21"
		}
	},
	"screenshots": [
		{
			"upper": "https://kanzashi-wup.cdn.nintendo.net/i/a1f6d83e59ea8496611f44dd60db8809c0a1e2293f8dfa5ddcdc964ab617db56.jpg",
			"lower": "https://kanzashi-wup.cdn.nintendo.net/i/a2f17a047a8c0660bea56ebab4fd2fad8f399adecfef9f1c8f558fa1c235c7fd.jpg"
		},
		{
			"upper": "https://kanzashi-wup.cdn.nintendo.net/i/027f4c876d409085074d6e5291cf70f4d9f8939cf547c1076b958ea5d2878ec5.jpg",
			"lower": "https://kanzashi-wup.cdn.nintendo.net/i/6d8c109e91d1ea9f46dc41392c86bc90914aac308067dded7b268403603848bd.jpg"
		},
		{
			"upper": "https://kanzashi-wup.cdn.nintendo.net/i/ef6ab0ef9f0fd44bd4bb7de0e03d8bdcbec08191b5eb02332ea55072ff38d4d2.jpg",
			"lower": "https://kanzashi-wup.cdn.nintendo.net/i/834a87806de581950ea1f5e53daf359da45e0e11bc1c8af7f0bada33136d847b.jpg"
		}
	],
	"movies": []
}