{
	"title_id": "0004000000034C00",
	"eshop_id": "50010000000257",
	"product_code": "CTR-P-ASFE",
	"name": "Asphalt™ 3D",
	"platform": 18,
	"platform_device": "CTR",
	"publisher": 278,
	"banner_url": null,
	"icon_url": "https://kanzashi-wup.cdn.nintendo.net/i/2a774308d8ba8eb6c50cbdc7324a9c462096f17c8f9ab7ebf7a27d694b63c16e.jpg",
	"data_size": null,
	"description": "¡Asphalt 3D son carreras como jamás se han experimentado antes! Gráficos totalmente en 3D y modelos auténticos de vehículos hacen de esta la experiencia más realista y envolvente jamás experimentada. En Asphalt 3D podrás elegir entre 40 vehículos de alto rendimiento y podrás correr por 17 exóticas locaciones en ambos modos de juego, modo carrera y modo multijugador. Experimenta la emoción de la pista en 3D mientras tratas de evadir el tráfico que viene en sentido contrario. Revela nuevas pistas y vehículos, personaliza tu vehículo y ¡hasta 6 amigos pueden jugar utilizando el modo de juego local de Nintendo 3DS! Activa StreetPass para enviar y recibir datos de juego y poder compararte con tus amigos y prácticamente con cualquier persona que juegue este juego. Juega una carrera en contra del fantasma viral de los jugadores con las mejores puntuaciones y alcanza la cima de los marcadores para ganar dinero del juego. ",
	"availability": {
		"eshop": false,
		"retail": true,
		"dates": {
			"eshop": null,
			"retail": "2011-03-27"
		}
	},
	"screenshots": [
		{
			"upper": "https://kanzashi-wup.cdn.nintendo.net/i/a35556c9f62f8d359d584434b0b1e760a9d12d055996451d3cc9c38bfdbf7629.jpg",
			"lower": "https://kanzashi-wup.cdn.nintendo.net/i/77d36fb87e0629c038115181795b08ff42aa9538faeced6c0702480fa28c755f.jpg"
		},
		{
			"upper": "https://kanzashi-wup.cdn.nintendo.net/i/f8a5904030e35db6630de23f458f9a40d424ef013fd7bdfcb29faf17bc81c332.jpg",
			"lower": "https://kanzashi-wup.cdn.nintendo.net/i/f402eaac4e3232f24408637c71eded2442865292cb298c8e1fee7d0b8dc57f59.jpg"
		},
		{
			"upper": "https://kanzashi-wup.cdn.nintendo.net/i/756e31dbbca1878bf257d7c2455611a43f366cacf7c85e707a6f766519dac32f.jpg",
			"lower": "https://kanzashi-wup.cdn.nintendo.net/i/6b8ea7fce4d9c613db1ec25846b75b384af3784866a6360e78c19beb40489f2f.jpg"
		}
	],
	"movies": []
}