{
	"title_id": "000500001016A500",
	"eshop_id": "20010000023027",
	"product_code": "WUP-N-PPAP",
	"name": "R-TYPE™",
	"platform": 166,
	"platform_device": "WUP",
	"publisher": 149,
	"banner_url": "https://kanzashi-wup.cdn.nintendo.net/i/16d818efb9134eac1360ad565a092acdbdf9a45430e99104e5e6bdae5943d5c9.jpg",
	"icon_url": "https://kanzashi-wup.cdn.nintendo.net/i/0d4f044453a0b6c6ef904ebb6fc945caf41033e0a822c8b7408799ea73423e1d.jpg",
	"data_size": "230097036",
	"description": "R-TYPE – einer der beliebtesten Arcade-Shooter aller Zeiten in einer pixelgenauen Umsetzung! Zerstörte POW-Kapseln setzen eines von sechs verschiedenen Extra-Items zum Aufrüsten des eigenen R-9-Jägers frei. Die Force, ein hoch entwickeltes Angriffsmodul, ist ein unerlässliches Hilfsmittel im Kampf gegen die außerirdische Bedrohung: Geschickte Piloten koppeln sie von ihrem R-9 ab und schicken sie auf Gegnerjagd oder bestücken sie mit zahlreichen Extrawaffen wie Reflektor-Laser, Luft-Boden- oder Flugabwehrraketen. Ein längerer Druck auf den Feuerknopf aktiviert die Beam-Kanone: Wer es schafft, diese mächtige Wunderwaffe lange genug aufzuladen, entfesselt einen Energiestoß, in dem jeder Widerstand verglüht! Die unbestrittenen Höhepunkte dieses Meisterwerks sind die bildschirmfüllenden Endgegner und der legendäre dritte Level, in dem der Spieler allein gegen ein monströses Schlachtschiff bestehen muss. Wenn du diesen Titel bereits auf deiner Wii™ erworben hast, führe einen System-Transfer von deiner Wii auf deine Wii U™ durch, um ein Upgrade-Sonderangebot zu erhalten.",
	"availability": {
		"eshop": true,
		"retail": false,
		"dates": {
			"eshop": "2016-07-28",
			"retail": null
		}
	},
	"screenshots": [
		"https://kanzashi-wup.cdn.nintendo.net/i/0e6b9e958255fd5170eb9cd1f8c4b1f35cedf0b0f6abfe80f3bf289fd119b584.jpg",
		"https://kanzashi-wup.cdn.nintendo.net/i/db80dcce2918ff06011a18981b4796163f8557b019ba28d0df2ceffb086f4007.jpg",
		"https://kanzashi-wup.cdn.nintendo.net/i/c83cf790ef4a31b11500edd883200b4932496605653da62ab2171a2fff7b3556.jpg",
		"https://kanzashi-wup.cdn.nintendo.net/i/60b5a85371bc5e4fde0d8989e5527b7841c939734b1c1d3a88828de179282dd8.jpg",
		"https://kanzashi-wup.cdn.nintendo.net/i/d8fd57fac9b1bde3e0b1b1755ef86a5101ca278ed860b7dde6424dc51e173484.jpg",
		"https://kanzashi-wup.cdn.nintendo.net/i/74308709e2c72c5a14c91ca770476c561780c75886c309079275fd0eaaae441f.jpg"
	],
	"movies": [
		{
			"banner_url": "https://kanzashi-wup.cdn.nintendo.net/i/db6967a35459e5efdc558073d81b59c8885ca8368a53d180c43c0f3d6246b382.jpg",
			"name": "R-TYPE™: Video",
			"files": [
				{
					"quality": "HQ",
					"format": "mp4",
					"movie_url": "https://kanzashi-movie-wup.cdn.nintendo.net/m/563cfd45a406c4fc9a24212e68595cb95132f6ad2182d3b7bbc136695e32443f.mp4",
					"width": "1280",
					"height": "720",
					"dimension": "2d",
					"play_time_sec": "59"
				},
				{
					"quality": "LQ",
					"format": "mp4",
					"movie_url": "https://kanzashi-movie-wup.cdn.nintendo.net/m/4120cdf0071ef2e96c5eac81a832aa9f3a34e0814f8575155bbf89e256b59665.mp4",
					"width": "854",
					"height": "480",
					"dimension": "2d",
					"play_time_sec": "59"
				}
			]
		}
	]
}