{
	"title_id": "0005000010165E00",
	"eshop_id": "20010000027148",
	"product_code": "WUP-N-PNNP",
	"name": "Shockman",
	"platform": 166,
	"platform_device": "WUP",
	"publisher": 81,
	"banner_url": "https://kanzashi-wup.cdn.nintendo.net/i/79467ea1ebc68eb35607d20a395757343e93e5b9e65faddc821430ebda35d2a6.jpg",
	"icon_url": "https://kanzashi-wup.cdn.nintendo.net/i/fb5f3b6a56418df3113f413b9bd42a5d0be4c2967dc9f2ce40f83bcd858babb1.jpg",
	"data_size": "229638284",
	"description": "Прошло два года с тех пор, как Арнольда и Соню сделали «шокменами». Получив от профессора сообщение с просьбой «вернуться в свои тела», они идут в его лабораторию, но по пути попадают в засаду, устроенную неизвестным врагом. Им удается выбраться из западни, но затем они видят по телевизору экстренные новости о вторжении империи RYO EMPIRE. Они узнают, что профессор похищен, и отправляются спасать его. Shockman — экшн-шутер с видом сбоку. Он состоит из 8 уровней, в том числе уровней Action Stage, где вы прыгаете и используете спецприемы, и уровней с боковой прокруткой Shooting Stage. Игра раскрывает стремительный сюжет предыдущей версии и содержит элементы совместной игры, например «общую жизнь» и мощный прием Team Shockbeam, который два игрока могут выполнить только вместе. Если вы приобрели игру на Wii™, вы можете передать ее на консоль Wii U™ и получить скидку на обновление игры до версии Wii U.",
	"availability": {
		"eshop": true,
		"retail": false,
		"dates": {
			"eshop": "2017-09-28",
			"retail": null
		}
	},
	"screenshots": [
		"https://kanzashi-wup.cdn.nintendo.net/i/944bd5d29838cd4b1442a1b8b5d011241ec5f7ea44672cedf19278a0d986923a.jpg",
		"https://kanzashi-wup.cdn.nintendo.net/i/51b82bb7606d29d0b63686bbd9333fe79fe96e7470a8702f65be3bb99809dc67.jpg",
		"https://kanzashi-wup.cdn.nintendo.net/i/d2230bfaede448d461e8744ad2e46cb11d81171f8aad87e850fd4886a35de937.jpg"
	],
	"movies": [
		{
			"banner_url": "https://kanzashi-wup.cdn.nintendo.net/i/66c4c3dcc3cc6aafa9fd48d1115fa05ceeae5a4b408106f5e130e49d7f1daba7.jpg",
			"name": "Shockman: видео",
			"files": [
				{
					"quality": "HQ",
					"format": "mp4",
					"movie_url": "https://kanzashi-movie-wup.cdn.nintendo.net/m/fd616fa140aa9741ea6d01722207777b393badd85365565789ba26fd2aa24c35.mp4",
					"width": "1280",
					"height": "720",
					"dimension": "2d",
					"play_time_sec": "42"
				}
			]
		}
	]
}